HISTORY.md
LICENSE
MANIFEST.in
NOTICE
README.md
setup.py
aiter/__init__.py
aiter/active_aiter.py
aiter/aiter_forker.py
aiter/aiter_to_iter.py
aiter/azip.py
aiter/deferred_coroutine.py
aiter/event_stream.py
aiter/flatten_aiter.py
aiter/gated_aiter.py
aiter/iter_to_aiter.py
aiter/join_aiters.py
aiter/map_aiter.py
aiter/map_filter_aiter.py
aiter/parallel_map_aiter.py
aiter/preload_aiter.py
aiter/push_aiter.py
aiter/server.py
aiter/sharable_aiter.py
aiter/simple_map_aiter.py
aiter/stoppable_aiter.py
aiter.egg-info/PKG-INFO
aiter.egg-info/SOURCES.txt
aiter.egg-info/dependency_links.txt
aiter.egg-info/top_level.txt